macleod/.gitignore
macleod/Clif.py
macleod/ClifLemmaSet.py
macleod/ClifModule.py
macleod/ClifModuleSet.py
macleod/ColoreOutputCleaner.py
macleod/ColoreProver.py
macleod/ColoreProverlib.py
macleod/Commands.py
macleod/Filemgt.py
macleod/LICENCE.txt
macleod/Ladr.py
macleod/Ontology.py
macleod/Process.py
macleod/ProofStatistic.py
macleod/README.md
macleod/Reasoner.py
macleod/ReasonerSet.py
macleod/Vampire.py
macleod/__init__.py
macleod/pylintrc
macleod/requirements.txt
macleod/setup.py
macleod/.github/workflows/linting-testing.yml
macleod/UMaine Capstone Documents/RCD_CDRD.pdf
macleod/UMaine Capstone Documents/RCD_SDD_Ver_1.1.pdf
macleod/UMaine Capstone Documents/RCD_SRS_Ver_1.3.pdf
macleod/UMaine Capstone Documents/RCD_UIDD.pdf
macleod/build/lib/macleod/Clif.py
macleod/build/lib/macleod/ClifLemmaSet.py
macleod/build/lib/macleod/ClifModule.py
macleod/build/lib/macleod/ClifModuleSet.py
macleod/build/lib/macleod/ColoreOutputCleaner.py
macleod/build/lib/macleod/ColoreProver.py
macleod/build/lib/macleod/Commands.py
macleod/build/lib/macleod/Filemgt.py
macleod/build/lib/macleod/Ladr.py
macleod/build/lib/macleod/Ontology.py
macleod/build/lib/macleod/Process.py
macleod/build/lib/macleod/ProofStatistic.py
macleod/build/lib/macleod/Reasoner.py
macleod/build/lib/macleod/ReasonerSet.py
macleod/build/lib/macleod/Vampire.py
macleod/build/lib/macleod/__init__.py
macleod/build/lib/macleod/dl/__init__.py
macleod/build/lib/macleod/dl/filters.py
macleod/build/lib/macleod/dl/owl.py
macleod/build/lib/macleod/dl/patterns.py
macleod/build/lib/macleod/dl/translation.py
macleod/build/lib/macleod/dl/utilities.py
macleod/build/lib/macleod/gui/Arborist.py
macleod/build/lib/macleod/gui/__init__.py
macleod/build/lib/macleod/gui/gui_alpha.py
macleod/build/lib/macleod/gui/summary.py
macleod/build/lib/macleod/gui/table.py
macleod/build/lib/macleod/gui/gui_beta/__init__.py
macleod/build/lib/macleod/gui/gui_beta/gui_filehelper.py
macleod/build/lib/macleod/gui/gui_beta/gui_highlighter.py
macleod/src/Macleod.egg-info/PKG-INFO
macleod/src/Macleod.egg-info/SOURCES.txt
macleod/src/Macleod.egg-info/dependency_links.txt
macleod/src/Macleod.egg-info/entry_points.txt
macleod/src/Macleod.egg-info/not-zip-safe
macleod/src/Macleod.egg-info/requires.txt
macleod/src/Macleod.egg-info/top_level.txt
macleod-0.2.8.dist-info/METADATA
macleod-0.2.8.dist-info/WHEEL
macleod-0.2.8.dist-info/RECORD
